numerosprimosDavid/NumerosPrimos1-n.py
numerosprimosDavid-0.1.dist-info/LICENSE.txt
numerosprimosDavid-0.1.dist-info/METADATA
numerosprimosDavid-0.1.dist-info/WHEEL
numerosprimosDavid-0.1.dist-info/top_level.txt
numerosprimosDavid-0.1.dist-info/RECORD
