Metadata-Version: 2.1
Name: numerosprimosDavid
Version: 0.1
Summary: A tool to perform mathematical operations.
Home-page: UNKNOWN
Author: David Cadena
Author-email: dc1020mw2@gmail.com
License: GNU GPLv3
Keywords: pyoperaciones numeros primos
Platform: UNKNOWN
Classifier: Development Status :: 4 - Beta
Classifier: Intended Audience :: Developers
Classifier: Topic :: Utilities
Classifier: License :: OSI Approved :: GNU General Public License v3 (GPLv3)
Classifier: Programming Language :: Python :: 3
Classifier: Operating System :: OS Independent
